mkdocs_extract_listings_plugin/__init__.py
mkdocs_extract_listings_plugin/all_listings_page.py
mkdocs_extract_listings_plugin/default.css
mkdocs_extract_listings_plugin/html_parser.py
mkdocs_extract_listings_plugin/listing-search.js
mkdocs_extract_listings_plugin/page_processor.py
mkdocs_extract_listings_plugin/search_page.py
mkdocs_extract_listings_plugin-0.2.1.dist-info/licenses/LICENSE
mkdocs_extract_listings_plugin-0.2.1.dist-info/METADATA
mkdocs_extract_listings_plugin-0.2.1.dist-info/WHEEL
mkdocs_extract_listings_plugin-0.2.1.dist-info/entry_points.txt
mkdocs_extract_listings_plugin-0.2.1.dist-info/top_level.txt
mkdocs_extract_listings_plugin-0.2.1.dist-info/RECORD
